<odoo>
    <data>
    <menuitem name="CAFRAD"
              id="cafrad_app.menu_root"
              groups="base.group_user"
              action="cafrad_app.view_create_apprenant_cafrad_action"/>

    <!-- !!!!!!!!!!!!!!!!!!!!!! MENU APPRENANTS!!!!!!!!!!!!!!!!!!!!!!!!!!!!!!!! -->

        <menuitem name="Prospets/Apprenants"
                  id="cafrad_app.apprenants"
                  parent="cafrad_app.menu_root"
                  sequence="2"
                  groups="base.group_user"/>

            <menuitem name="Enregistrer un nouveau Prospet/Apprenant"
                      id="cafrad_app.create_apprenant"
                      parent="cafrad_app.apprenants"
                      sequence="3"
                      groups="base.group_user"
                      action="cafrad_app.view_create_apprenant_cafrad_action"/>


            <menuitem name="Tous les Prospets"
                      id="cafrad_app.all_prospects"
                      parent="cafrad_app.apprenants"
                      groups="base.group_user"
                      sequence="4"
                      action="cafrad_app.view_all_prospect_cafrad_action"/>
                      

            <menuitem name="Tous les apprenants"
                      id="cafrad_app.all_aprenants"
                      parent="cafrad_app.apprenants"
                      groups="base.group_user"
                      sequence="5"
                      action="cafrad_app.view_all_apprenant_cafrad_action"/>

        <!-- !!!!!!!!!!!!!!!!!!!!!! MENU EDUCATION DE BASE!!!!!!!!!!!!!!!!!!!!!!!!!!!!!!!! -->

            <menuitem name="GROUPE SCOLAIRE"
                      id="cafrad_app.educatiion_base"
                      parent="cafrad_app.apprenants"
                      groups="base.group_user"
                      sequence="4"
                      action="cafrad_app.view_apprenant_groupe_scolaire_cafrad_action"/>

                      
<!--                       <menuitem name="Maternelle 1"-->
<!--                                  id="cafrad_app.aprrenant_maternel1"-->
<!--                                  parent="cafrad_app.educatiion_base"-->
<!--                                  groups="base.group_user"-->
<!--                                  sequence="5"-->
<!--                                  action="cafrad_app.view_apprenant_maternel1_cafrad_action"/>-->
<!--                       <menuitem name="Maternelle 2"-->
<!--                                  id="cafrad_app.aprrenant_materiel2"-->
<!--                                  parent="cafrad_app.educatiion_base"-->
<!--                                  groups="base.group_user"-->
<!--                                  sequence="6"-->
<!--                                  action="cafrad_app.view_apprenant_maternel2_cafrad_action"/>-->

<!--                        <menuitem name="Maternelle 3"-->
<!--                                  id="cafrad_app.aprrenant_maternel3"-->
<!--                                  parent="cafrad_app.educatiion_base"-->
<!--                                  groups="base.group_user"-->
<!--                                  sequence="7"-->
<!--                                  action="cafrad_app.view_apprenant_maternel3_cafrad_action"/>-->

<!--                       <menuitem name="SIL"-->
<!--                                  id="cafrad_app.aprrenant_sil"-->
<!--                                  parent="cafrad_app.educatiion_base"-->
<!--                                  groups="base.group_user"-->
<!--                                  sequence="8"-->
<!--                                  action="cafrad_app.view_apprenant_sil_cafrad_action"/>-->

<!--                      <menuitem name="CP"-->
<!--                                  id="cafrad_app.aprrenant_cp"-->
<!--                                  parent="cafrad_app.educatiion_base"-->
<!--                                  groups="base.group_user"-->
<!--                                  sequence="9"-->
<!--                                  action="cafrad_app.view_apprenant_cp_cafrad_action"/>-->


<!--                      <menuitem name="CE1"-->
<!--                                  id="cafrad_app.aprrenant_ce1"-->
<!--                                  parent="cafrad_app.educatiion_base"-->
<!--                                  groups="base.group_user"-->
<!--                                  sequence="10"-->
<!--                                  action="cafrad_app.view_apprenant_ce1_cafrad_action"/>-->

<!--                      <menuitem name="CE2"-->
<!--                                  id="cafrad_app.aprrenant_ce2"-->
<!--                                  parent="cafrad_app.educatiion_base"-->
<!--                                  groups="base.group_user"-->
<!--                                  sequence="11"-->
<!--                                  action="cafrad_app.view_apprenant_ce2_cafrad_action"/>-->

<!--                      <menuitem name="CM1"-->
<!--                                  id="cafrad_app.aprrenant_cm1"-->
<!--                                  parent="cafrad_app.educatiion_base"-->
<!--                                  groups="base.group_user"-->
<!--                                  sequence="12"-->
<!--                                  action="cafrad_app.view_apprenant_cm1_cafrad_action"/>-->

<!--                      <menuitem name="CM2"-->
<!--                                  id="cafrad_app.aprrenant_cm2"-->
<!--                                  parent="cafrad_app.educatiion_base"-->
<!--                                  sequence="13"-->
<!--                                  groups="base.group_user"-->
<!--                                  action="cafrad_app.view_apprenant_cm2_cafrad_action"/>-->

<!-- !!!!!!!!!!!!!!!!!!!!!! MENU CEF!!!!!!!!!!!!!!!!!!!!!!!!!!!!!!!! -->

            <menuitem name="FORMATION CEF"
                      id="cafrad_app.cef_formations"
                      parent="cafrad_app.apprenants"
                      groups="base.group_user"
                      action="cafrad_app.view_apprenant_cef__cafrad_action"
                      sequence="14"/>


<!--                <menuitem name="HOTELLERIE 6 mois"-->
<!--                          id="cafrad_app.formation_hotellerie6m"-->
<!--                          parent="cafrad_app.cef_formations"-->
<!--                          groups="base.group_user"-->
<!--                          action="cafrad_app.view_apprenant_h6m_cafrad_action"-->
<!--                          sequence="15"/>-->

<!--                <menuitem name="HOTELLERIE  1 an "-->
<!--                          id="cafrad_app.formation_hotellerie1an"-->
<!--                          parent="cafrad_app.cef_formations"-->
<!--                          groups="base.group_user"-->
<!--                          action="cafrad_app.view_apprenant_h1an_cafrad_action"-->
<!--                          sequence="15"/>-->

<!--                <menuitem name="COUTURE 1"-->
<!--                          id="cafrad_app.formation_couture1"-->
<!--                          parent="cafrad_app.cef_formations"-->
<!--                          sequence="16"-->
<!--                          action="cafrad_app.view_apprenant_couture1_cafrad_action"-->
<!--                          groups="base.group_user"/>-->

<!--                <menuitem name="COUTURE 2"-->
<!--                          id="cafrad_app.formation_couture2"-->
<!--                          parent="cafrad_app.cef_formations"-->
<!--                          sequence="17"-->
<!--                          action="cafrad_app.view_apprenant_couture2_cafrad_action"-->
<!--                          groups="base.group_user"/>-->
<!--                <menuitem name="COUTURE 3"-->
<!--                          id="cafrad_app.formation_couture3"-->
<!--                          parent="cafrad_app.cef_formations"-->
<!--                          sequence="18"-->
<!--                          action="cafrad_app.view_apprenant_couture3_cafrad_action"-->
<!--                          groups="base.group_user"/>-->

<!--                <menuitem name="PATISSERIE 6 mois"-->
<!--                          id="cafrad_app.cef_patis6m"-->
<!--                          parent="cafrad_app.cef_formations"-->
<!--                          sequence="19"-->
<!--                          action="cafrad_app.view_apprenant_patis6m_cafrad_action"-->
<!--                          groups="base.group_user"/>-->

<!--                <menuitem name="PATISSERIE 1 an"-->
<!--                          id="cafrad_app.cef_patis6m"-->
<!--                          parent="cafrad_app.cef_formations"-->
<!--                          sequence="20"-->
<!--                          action="cafrad_app.view_apprenant_patis1an_cafrad_action"-->
<!--                          groups="base.group_user"/>-->



<!-- !!!!!!!!!!!!!!!!!!!!!! MENU FORMATION CAFRAD!!!!!!!!!!!!!!!!!!!!!!!!!!!!!!!! -->

            <menuitem name="FORMATIONS BEPANDA"
                      id="cafrad_app.formation_cafrad"
                      parent="cafrad_app.apprenants"
                      sequence="21"
                      action="cafrad_app.view_apprenant_bependa_cafrad_action"
                      groups="base.group_user"/>

<!--            <menuitem name="GARAGE"-->
<!--                      id="cafrad_app.garage"-->
<!--                      parent="cafrad_app.formation_cafrad"-->
<!--                      sequence="22"-->
<!--                      action="cafrad_app.view_apprenant_garage_cafrad_action"-->
<!--                      groups="base.group_user"/>-->


            <menuitem name="AUTRES FORMATIONS"
                      id="cafrad_app.formation_cafrad"
                      parent="cafrad_app.apprenants"
                      sequence="23"
                      action="cafrad_app.view_apprenant_other_formation_cafrad_action"
                      groups="base.group_user"/>

            <menuitem name="FORMATIONS EXTERNES"
                      id="cafrad_app.formation_cafrad"
                      parent="cafrad_app.apprenants"
                      sequence="23"
                      action="cafrad_app.view_apprenant_externe_cafrad_action"
                      groups="base.group_user"/>



            <menuitem name="Admissions"
                      id="cafrad_app.admissions"
                      parent="cafrad_app.menu_root"
                      sequence="24"
                      action="cafrad_app.view_apprenant_upgrade_cafrad_action"
                      groups="base.group_user"/>


        <menuitem name="Suivi Des Formations"
                  id="cafrad_app.suivi"
                  parent="cafrad_app.menu_root"
                  sequence="25"
                  groups="base.group_user"/>
             <menuitem name="Suivi et Insertion"
                       id="cafrad_app.suivi_insert"
                       parent="cafrad_app.suivi"
                       sequence="26"
                       groups="base.group_user"/>

                    <menuitem name="Apprenants"
                              id="cafrad_app.aprrenant_non_handicap"
                              parent="cafrad_app.suivi_insert"
                              groups="base.group_user"
                              sequence="27"
                              action="cafrad_app.view_apprenant_not_handicap_cafrad_action"/>
                    <menuitem name="Fiche de suivi"
                              id="cafrad_app.fiche_suivi"
                              parent="cafrad_app.suivi_insert"
                              groups="base.group_user"
                              sequence="31"
                              action="cafrad_app.view_fiche_suivi_cafrad_action"/>



            <menuitem name="Actions Diaconnales"
                      id="cafrad_app.suivi_diaco"
                      parent="cafrad_app.suivi"
                      sequence="28"
                      groups="base.group_user"/>

            <menuitem name="Apprenants Handicapés"
                      id="cafrad_app.aprrenant_handicap"
                      parent="cafrad_app.suivi_diaco"
                      groups="base.group_user"
                      sequence="29"
                      action="cafrad_app.view_apprenant_handicap_cafrad_action"/>

            <menuitem name="Fiche de suivi"
                      id="cafrad_app.fiche_suivi2"
                      parent="cafrad_app.suivi_diaco"
                      groups="base.group_user"
                      sequence="30"
                      action="cafrad_app.view_fiche_suivi_cafrad_action"/>




        <menuitem name="Emplois de Temps"
                  id="cafrad_app.time_table"
                  parent="cafrad_app.menu_root"
                  groups="base.group_user"
                  sequence="32"
                  action="view_time_table_cafrad_action"/>

        <menuitem name="Médiathèque"
                  id="cafrad_app.book_loan"
                  parent="cafrad_app.menu_root"
                  groups="base.group_user"
                  sequence="32"
                  action="cafrad_app.view_mediatek_cafrad_action"/>

        <menuitem name="Magazine"
                  id="cafrad_app.magazine"
                  parent="cafrad_app.menu_root"
                  groups="base.group_user"
                  sequence="32"
                  action="cafrad_app.view_magazine_cafrad_action"/>

        <menuitem name="Radio"
                  id="cafrad_app.radio"
                  parent="cafrad_app.menu_root"
                  groups="base.group_user"
                  sequence="33"
                  action="cafrad_app.view_radio_cafrad_action"/>



        <menuitem name=" Sui des Projets"
                  id="cafrad_app.suivi_projets"
                  parent="cafrad_app.menu_root"
                  groups="base.group_user"
                  sequence="35"
                  action="cafrad_app.view_suivi_projet_cafrad_action"/>

<!--        <menuitem name="Presences"-->
<!--                  id="cafrad_app.presences"-->
<!--                  parent="cafrad_app.menu_root"-->
<!--                  groups="base.group_user"-->
<!--                  sequence="34"-->
<!--                  action="cafrad_app.view_employe_presence_cafrad_action"/>-->




        <!-- Configurations -->

       <menuitem name="Configurations"
                  id="cafrad_app.config"
                  parent="cafrad_app.menu_root"
                  sequence="36"

                  />
            <menuitem name="Annees Academiques"
                      id="cafrad_app.ana_academique"
                      parent="cafrad_app.config"
                      action="cafrad_app.view_ane_academiq_action"/>

            <menuitem name="Religions"
                      id="cafrad_app.religion"
                      parent="cafrad_app.config"
                      action="cafrad_app.view_religion_cafrad_action"/>


            <menuitem name="Regions"
                      id="cafrad_app.region"
                      parent="cafrad_app.config"
                      action="cafrad_app.view_region_cafrad_action"/>

            <menuitem name="Filieres"
                      id="cafrad_app.speciality"
                      parent="cafrad_app.config"
                      action="cafrad_app.view_speciality_cafrad_action"/>


            <menuitem name="Salle de classe"
                      id="cafrad_app.salle_classe"
                      parent="cafrad_app.config"
                      action="cafrad_app.view_salle_classe_cafrad_action"/>\

            <menuitem name="Enseignants"
                      id="cafrad_app.teacher"
                      parent="cafrad_app.config"
                      action="cafrad_app.view_teacher_cafrad_action"/>


            <menuitem name="Livres"
                      id="cafrad_app.book"
                      parent="cafrad_app.config"
                      action="cafrad_app.view_livre_cafrad_action"/>

            <menuitem name="Categories de livres"
                      id="cafrad_app.book_categorie"
                      parent="cafrad_app.config"
                      action="cafrad_app.view_categori_book_cafrad_action"/>

            <menuitem name="Emissions Radio"
                      id="cafrad_app.emission_radio"
                      parent="cafrad_app.config"
                      action="cafrad_app.view_emission_radio_cafrad_action"/>

            <menuitem name="Projets"
                      id="cafrad_app.projets"
                      parent="cafrad_app.config"
                      groups="base.group_user"
                      action="cafrad_app.view_projet_cafrad_action" />
            <menuitem name="Types de paiements"
                      id="cafrad_app.tyep_payments"
                      parent="cafrad_app.config"
                      groups="base.group_user"
                      action="cafrad_app.view_payment_type_cafrad_action" />
    </data>

</odoo>